<?xml version="1.0" encoding="iso-8859-1"?><Principal><Atendimento><Cliente><Nome>MARIA DE LOURDES TEIXEIRA SERRA</Nome><Senha>6046b4</Senha><Email></Email><DDDCelular>21</DDDCelular><Celular></Celular><DDDTelResidencia>21</DDDTelResidencia><TelResidencia>2241-3874</TelResidencia></Cliente><Laudo><Visita>040</Visita><CodigoExterno>0796156040</CodigoExterno><DataAtendimento>25/08/2012</DataAtendimento><Status>2</Status><SMSAutomatico>0</SMSAutomatico><EmailAutomatico>1</EmailAutomatico><FaxAutomatico>0</FaxAutomatico><ImpressaoAutomatica>1</ImpressaoAutomatica><ExibeLaudoCliente>1</ExibeLaudoCliente><ExibeLaudoMedico>0</ExibeLaudoMedico><ExibeLaudoEmpresa>0</ExibeLaudoEmpresa><MedicoExecutante><Codigo>010</Codigo></MedicoExecutante><MedicoRequisitante><Codigo>52810924</Codigo><Nome>ALEXANDRE DOS SANTOS</Nome></MedicoRequisitante><Empresa><Codigo>001</Codigo><Nome>PRONTO LAB LABORATORIO DE A. CLINICAS</Nome><Senha></Senha><Email></Email></Empresa><Conteudo><![CDATA[<PRE><B>NIC: </B>0796156/040<BR><B>DATA: </B>25/08/2012<BR><B>NOME: </B>MARIA DE LOURDES TEIXEIRA SERRA<BR><B>TEL: </B>2241-3874<BR><B>END.: </B>CHAVES FARIAS 64 - SAO CRISTOVAO - RIO DE JANEIRO<BR><B>MEDICO: </B>ALEXANDRE DOS SANTOS<BR><BR><br><BR><B>CALCIO                        </B>13,1                mg/dL     Valores de Referencia</br><br>Método:Colorimetrico       </br><br>                                                            8,8 a 11,0 mg/dL    </br><br><BR><B>LIPIDOGRAMA                   </B>-                                                 </br><br>Aspecto do Soro               Limpido                                           </br><br>Colesterol Total              203,0               mg/dL                         </br><br>Triglicerideos                98,0                mg/dL                         </br><br>Fosfolipideos                 250,0               mg/dL                         </br><br>Lipideos Totais               563,0               mg/dL                         </br><br>ELETROFORESE DE LIPOPROTEINAS                                                   </br><br>Quilomicrons                  00,0                %                             </br><br>Beta Lipoproteinas            51,2                %                             </br><br>Pre Beta Lipoproteinas        17,4                %                             </br><br>Alfa Lipoproteinas            31,4                %                             </br><br><BR><B>TSH - ULTRA SENSIVEL          </B>1,90                mcUI/mL   Valores de Referencia :</br><br>Método:Imunoenzimometrico  </br><br>                                                            Eutiroidismo : 0,5 - 4,0 mcUI/mL</br><br>                                                            Hipertiroidismo : < 0,4  mcUI/mL</br><br>                                                            Hipotiroidismo : > 5,0 mcUI/mL</br><br>                                                            Atenção :  Novos valores de referencia</br><br>                                                            apartir de 27/12/2011.</br><br><BR><B>PTH - PARATHORMONIO           </B>28,6                pg/mL     Valor de Referencia </br><br>Método:Eletroquimioluminesc</br><br>                                                            12,0 a 72,0 pg/mL   </br><br><BR><B>VITAMINA D - 25 HIDROXI       </B>17,8                ng/mL     Valor de referencia :</br><br>Método:Quimioluminescencia </br><br>                                                            30,0 a 100,0 ng/mL  </br></PRE>]]></Conteudo></Laudo></Atendimento></Principal>
